vectabass/__init__.py
vectabass/package.py
vectabass-0.1.28.dist-info/LICENSE
vectabass-0.1.28.dist-info/METADATA
vectabass-0.1.28.dist-info/WHEEL
vectabass-0.1.28.dist-info/top_level.txt
vectabass-0.1.28.dist-info/RECORD
